ape_boba/__init__.py
ape_boba/ecosystem.py
ape_boba/py.typed
ape_boba/version.py
ape_boba-0.1.0.dist-info/LICENSE
ape_boba-0.1.0.dist-info/METADATA
ape_boba-0.1.0.dist-info/WHEEL
ape_boba-0.1.0.dist-info/top_level.txt
ape_boba-0.1.0.dist-info/RECORD
