Metadata-Version: 2.1
Name: ape-boba
Version: 0.1.0
Summary: ape-boba: Ape Ecosystem Plugin for Boba
Home-page: https://github.com/koyo-finance/ape-boba
Author: Kōyō Finance
Author-email: contat@koyo.finance
License: MIT
Keywords: ethereum
Platform: UNKNOWN
Classifier: Development Status :: 5 - Production/Stable
Classifier: Intended Audience :: Developers
Classifier: License :: OSI Approved :: MIT License
Classifier: Natural Language :: English
Classifier: Operating System :: MacOS
Classifier: Operating System :: POSIX
Classifier: Programming Language :: Python :: 3
Classifier: Programming Language :: Python :: 3.7
Classifier: Programming Language :: Python :: 3.8
Classifier: Programming Language :: Python :: 3.9
Classifier: Programming Language :: Python :: 3.10
Requires-Python: >=3.7.2,<3.11
Requires-Dist: eth-ape (<0.3.0,>=0.2.1)
Requires-Dist: importlib-metadata ; python_version < "3.8"
Provides-Extra: dev
Requires-Dist: pytest (<7.0,>=6.0) ; extra == 'dev'
Requires-Dist: pytest-xdist ; extra == 'dev'
Requires-Dist: pytest-cov ; extra == 'dev'
Requires-Dist: hypothesis (<7.0,>=6.2.0) ; extra == 'dev'
Requires-Dist: black (<23.0,>=22.3.0) ; extra == 'dev'
Requires-Dist: mypy (<1.0,>=0.910) ; extra == 'dev'
Requires-Dist: flake8 (<4.0,>=3.8.3) ; extra == 'dev'
Requires-Dist: isort (<6.0,>=5.10.1) ; extra == 'dev'
Requires-Dist: setuptools ; extra == 'dev'
Requires-Dist: wheel ; extra == 'dev'
Requires-Dist: twine ; extra == 'dev'
Requires-Dist: commitizen ; extra == 'dev'
Requires-Dist: pre-commit ; extra == 'dev'
Requires-Dist: pytest-watch ; extra == 'dev'
Requires-Dist: IPython ; extra == 'dev'
Requires-Dist: ipdb ; extra == 'dev'
Provides-Extra: lint
Requires-Dist: black (<23.0,>=22.3.0) ; extra == 'lint'
Requires-Dist: mypy (<1.0,>=0.910) ; extra == 'lint'
Requires-Dist: flake8 (<4.0,>=3.8.3) ; extra == 'lint'
Requires-Dist: isort (<6.0,>=5.10.1) ; extra == 'lint'
Provides-Extra: release
Requires-Dist: setuptools ; extra == 'release'
Requires-Dist: wheel ; extra == 'release'
Requires-Dist: twine ; extra == 'release'
Provides-Extra: test
Requires-Dist: pytest (<7.0,>=6.0) ; extra == 'test'
Requires-Dist: pytest-xdist ; extra == 'test'
Requires-Dist: pytest-cov ; extra == 'test'
Requires-Dist: hypothesis (<7.0,>=6.2.0) ; extra == 'test'
